{
  "iteration": 61,
  "stage": "prover  (iteration 060 \u2014 Phase A step 6 *Path 2* / **substantive \u010cech acyclicity attempt**: hand the prover the substantive `basicOpenCover_isCechAcyclicCover_toModuleKSheaf` theorem in `Cohomology/MayerVietoris.lean`. Plan agent has *not* pre-verified any candidate proof body (per user instruction 2026-05-11). Prover may write whatever helper lemmas it needs internally, may leave transient sorries inside the proof body if the full extra-degeneracy / local-to-global argument exceeds one session's capacity. The mathematical strategy lives in `analogies/cech-koszul-precedent.md` (Stacks 01ED extra-degeneracy route) and the corresponding blueprint chapter.",
  "mode": "parallel",
  "startedAt": "2026-05-11T05:05:32Z",
  "plan": {
    "status": "done",
    "durationSecs": 396
  },
  "prover": {
    "status": "done",
    "durationSecs": 777
  },
  "provers": {
    "AlgebraicJacobian_Cohomology_MayerVietoris": {
      "file": "AlgebraicJacobian/Cohomology/MayerVietoris.lean",
      "status": "done"
    }
  },
  "review": {
    "status": "done",
    "durationSecs": 798
  },
  "sorry_count": 315,
  "finalize": {
    "innerGit": {
      "sha": "049e162"
    },
    "lake": {
      "ok": true,
      "durationSecs": 27
    },
    "blueprint": {
      "ok": true,
      "durationSecs": 6
    }
  },
  "completedAt": "2026-05-11T06:21:53Z",
  "wallTimeSecs": 4581
}