{
  "files": [
    {
      "file": "AlgebraicJacobian/Albanese/AlbaneseUP.lean",
      "count": 7,
      "lines": [
        183,
        250,
        300,
        335,
        373,
        417,
        458
      ],
      "occurrences": [
        {
          "line": 183,
          "column": 40
        },
        {
          "line": 250,
          "column": 3
        },
        {
          "line": 300,
          "column": 3
        },
        {
          "line": 335,
          "column": 3
        },
        {
          "line": 373,
          "column": 3
        },
        {
          "line": 417,
          "column": 3
        },
        {
          "line": 458,
          "column": 3
        }
      ]
    },
    {
      "file": "AlgebraicJacobian/Albanese/CodimOneExtension.lean",
      "count": 3,
      "lines": [
        1527,
        1724,
        1799
      ],
      "occurrences": [
        {
          "line": 1527,
          "column": 3
        },
        {
          "line": 1724,
          "column": 3
        },
        {
          "line": 1799,
          "column": 3
        }
      ]
    },
    {
      "file": "AlgebraicJacobian/Albanese/Thm32RationalMapExtension.lean",
      "count": 2,
      "lines": [
        155,
        294
      ],
      "occurrences": [
        {
          "line": 155,
          "column": 25
        },
        {
          "line": 294,
          "column": 5
        }
      ]
    },
    {
      "file": "AlgebraicJacobian/Cohomology/CechHigherDirectImage.lean",
      "count": 7,
      "lines": [
        222,
        229,
        305,
        328,
        448,
        456,
        548
      ],
      "occurrences": [
        {
          "line": 222,
          "column": 5
        },
        {
          "line": 229,
          "column": 5
        },
        {
          "line": 305,
          "column": 3
        },
        {
          "line": 328,
          "column": 3
        },
        {
          "line": 448,
          "column": 5
        },
        {
          "line": 456,
          "column": 3
        },
        {
          "line": 548,
          "column": 3
        }
      ]
    },
    {
      "file": "AlgebraicJacobian/Cohomology/CechHigherDirectImageUnconditional.lean",
      "count": 6,
      "lines": [
        165,
        523,
        589,
        705,
        745,
        813
      ],
      "occurrences": [
        {
          "line": 165,
          "column": 65
        },
        {
          "line": 523,
          "column": 9
        },
        {
          "line": 589,
          "column": 21
        },
        {
          "line": 705,
          "column": 3
        },
        {
          "line": 745,
          "column": 3
        },
        {
          "line": 813,
          "column": 21
        }
      ]
    },
    {
      "file": "AlgebraicJacobian/Cohomology/CechSectionIdentificationBase.lean",
      "count": 8,
      "lines": [
        561,
        563,
        565,
        930,
        931,
        1061,
        1420,
        1421
      ],
      "occurrences": [
        {
          "line": 561,
          "column": 7
        },
        {
          "line": 563,
          "column": 7
        },
        {
          "line": 565,
          "column": 5
        },
        {
          "line": 930,
          "column": 7
        },
        {
          "line": 931,
          "column": 7
        },
        {
          "line": 1061,
          "column": 5
        },
        {
          "line": 1420,
          "column": 10
        },
        {
          "line": 1421,
          "column": 14
        }
      ]
    },
    {
      "file": "AlgebraicJacobian/Cohomology/FlatBaseChange.lean",
      "count": 2,
      "lines": [
        866,
        888
      ],
      "occurrences": [
        {
          "line": 866,
          "column": 3
        },
        {
          "line": 888,
          "column": 3
        }
      ]
    },
    {
      "file": "AlgebraicJacobian/Cohomology/PresheafCech.lean",
      "count": 1,
      "lines": [
        313
      ],
      "occurrences": [
        {
          "line": 313,
          "column": 5
        }
      ]
    },
    {
      "file": "AlgebraicJacobian/Jacobian.lean",
      "count": 1,
      "lines": [
        188
      ],
      "occurrences": [
        {
          "line": 188,
          "column": 3
        }
      ]
    },
    {
      "file": "AlgebraicJacobian/Picard/FGAPicRepresentability.lean",
      "count": 7,
      "lines": [
        149,
        176,
        236,
        294,
        349,
        446,
        502
      ],
      "occurrences": [
        {
          "line": 149,
          "column": 4
        },
        {
          "line": 176,
          "column": 4
        },
        {
          "line": 236,
          "column": 4
        },
        {
          "line": 294,
          "column": 4
        },
        {
          "line": 349,
          "column": 4
        },
        {
          "line": 446,
          "column": 4
        },
        {
          "line": 502,
          "column": 4
        }
      ]
    },
    {
      "file": "AlgebraicJacobian/Picard/FlatteningStratification.lean",
      "count": 7,
      "lines": [
        294,
        338,
        367,
        399,
        445,
        487,
        530
      ],
      "occurrences": [
        {
          "line": 294,
          "column": 3
        },
        {
          "line": 338,
          "column": 3
        },
        {
          "line": 367,
          "column": 3
        },
        {
          "line": 399,
          "column": 3
        },
        {
          "line": 445,
          "column": 3
        },
        {
          "line": 487,
          "column": 3
        },
        {
          "line": 530,
          "column": 3
        }
      ]
    },
    {
      "file": "AlgebraicJacobian/Picard/GlueDescent.lean",
      "count": 3,
      "lines": [
        1990,
        1998,
        2045
      ],
      "occurrences": [
        {
          "line": 1990,
          "column": 3
        },
        {
          "line": 1998,
          "column": 3
        },
        {
          "line": 2045,
          "column": 3
        }
      ]
    },
    {
      "file": "AlgebraicJacobian/Picard/GrassmannianQuot.lean",
      "count": 4,
      "lines": [
        813,
        838,
        2305,
        3259
      ],
      "occurrences": [
        {
          "line": 813,
          "column": 3
        },
        {
          "line": 838,
          "column": 3
        },
        {
          "line": 2305,
          "column": 20
        },
        {
          "line": 3259,
          "column": 14
        }
      ]
    },
    {
      "file": "AlgebraicJacobian/Picard/IdentityComponent.lean",
      "count": 9,
      "lines": [
        479,
        595,
        635,
        707,
        743,
        784,
        837,
        855,
        880
      ],
      "occurrences": [
        {
          "line": 479,
          "column": 3
        },
        {
          "line": 595,
          "column": 3
        },
        {
          "line": 635,
          "column": 5
        },
        {
          "line": 707,
          "column": 3
        },
        {
          "line": 743,
          "column": 3
        },
        {
          "line": 784,
          "column": 3
        },
        {
          "line": 837,
          "column": 3
        },
        {
          "line": 855,
          "column": 3
        },
        {
          "line": 880,
          "column": 3
        }
      ]
    },
    {
      "file": "AlgebraicJacobian/Picard/Pic0AbelianVariety.lean",
      "count": 5,
      "lines": [
        149,
        171,
        190,
        209,
        238
      ],
      "occurrences": [
        {
          "line": 149,
          "column": 3
        },
        {
          "line": 171,
          "column": 3
        },
        {
          "line": 190,
          "column": 3
        },
        {
          "line": 209,
          "column": 3
        },
        {
          "line": 238,
          "column": 3
        }
      ]
    },
    {
      "file": "AlgebraicJacobian/Picard/QuotScheme.lean",
      "count": 14,
      "lines": [
        173,
        212,
        248,
        275,
        330,
        596,
        620,
        676,
        1065,
        1227,
        1278,
        1328,
        1731,
        2246
      ],
      "occurrences": [
        {
          "line": 173,
          "column": 3
        },
        {
          "line": 212,
          "column": 3
        },
        {
          "line": 248,
          "column": 3
        },
        {
          "line": 275,
          "column": 3
        },
        {
          "line": 330,
          "column": 3
        },
        {
          "line": 596,
          "column": 9
        },
        {
          "line": 620,
          "column": 9
        },
        {
          "line": 676,
          "column": 9
        },
        {
          "line": 1065,
          "column": 9
        },
        {
          "line": 1227,
          "column": 3
        },
        {
          "line": 1278,
          "column": 3
        },
        {
          "line": 1328,
          "column": 3
        },
        {
          "line": 1731,
          "column": 3
        },
        {
          "line": 2246,
          "column": 3
        }
      ]
    },
    {
      "file": "AlgebraicJacobian/Picard/SectionGradedRing.lean",
      "count": 8,
      "lines": [
        1610,
        1613,
        1616,
        1697,
        1701,
        2270,
        2641,
        3228
      ],
      "occurrences": [
        {
          "line": 1610,
          "column": 3
        },
        {
          "line": 1613,
          "column": 3
        },
        {
          "line": 1616,
          "column": 3
        },
        {
          "line": 1697,
          "column": 3
        },
        {
          "line": 1701,
          "column": 3
        },
        {
          "line": 2270,
          "column": 3
        },
        {
          "line": 2641,
          "column": 3
        },
        {
          "line": 3228,
          "column": 3
        }
      ]
    },
    {
      "file": "AlgebraicJacobian/Picard/TensorObjSubstrate/PullbackTensorComp.lean",
      "count": 2,
      "lines": [
        822,
        1060
      ],
      "occurrences": [
        {
          "line": 822,
          "column": 3
        },
        {
          "line": 1060,
          "column": 3
        }
      ]
    },
    {
      "file": "AlgebraicJacobian/Picard/TensorObjSubstrate.lean",
      "count": 3,
      "lines": [
        302,
        512,
        735
      ],
      "occurrences": [
        {
          "line": 302,
          "column": 9
        },
        {
          "line": 512,
          "column": 24
        },
        {
          "line": 735,
          "column": 3
        }
      ]
    },
    {
      "file": "AlgebraicJacobian/RiemannRoch/WeilDivisor.lean",
      "count": 2,
      "lines": [
        830,
        1138
      ],
      "occurrences": [
        {
          "line": 830,
          "column": 5
        },
        {
          "line": 1138,
          "column": 5
        }
      ]
    }
  ],
  "total": 101,
  "partial": false,
  "warnings": []
}
