{
  "iteration": 63,
  "stage": "prover",
  "mode": "parallel",
  "startedAt": "2026-06-10T07:20:15Z",
  "plan": {
    "status": "done",
    "sessionId": "33523472-4486-45ad-afff-2adfe54c8987",
    "durationSecs": 2013
  },
  "planValidate": {
    "status": "ok",
    "objectives": 2
  },
  "prover": {
    "status": "done",
    "durationSecs": 17900
  },
  "provers": {
    "AlgebraicJacobian_Cohomology_CechSectionIdentification": {
      "file": "AlgebraicJacobian/Cohomology/CechSectionIdentification.lean",
      "status": "done",
      "mode": "mathlib-build",
      "sessionId": "c3644161-dbfb-4f97-a36f-ced979be2168"
    },
    "AlgebraicJacobian_Cohomology_OpenImmersionPushforward": {
      "file": "AlgebraicJacobian/Cohomology/OpenImmersionPushforward.lean",
      "status": "done",
      "mode": "mathlib-build",
      "sessionId": "6cfa023c-2eca-42ff-9397-5104c8e44775"
    }
  },
  "review": {
    "status": "done",
    "sessionId": "4b6cadcb-250f-498b-97db-fb2a24242fdc",
    "durationSecs": 5930
  },
  "sorry_count": 9,
  "finalize": {
    "innerGit": {
      "sha": "2faba2a"
    },
    "lake": {
      "ok": true,
      "durationSecs": 6
    },
    "blueprint": {
      "ok": false,
      "durationSecs": 3,
      "error": "web"
    }
  },
  "completedAt": "2026-06-10T14:37:36Z",
  "wallTimeSecs": 26241
}