{
  "iteration": 62,
  "stage": "prover  (iteration 061 \u2014 Phase A step 6 *Path 2* / **second prover pass on the substantive \u010cech acyclicity theorem**: the iter-060 prover stated `basicOpenCover_isCechAcyclicCover_toModuleKSheaf`, closed the structural-reduction helper, and left one annotated transient sorry covering substeps (a)+(b)+(c) of the Stacks 01ED proof. Iter-061 returns the same theorem to the prover with directive to engage with one or more of the three substeps in this same session. Per user policy (2026-05-11), the plan agent does NOT extract substeps as standalone planner-iteration helpers; the prover folds substep helpers into its own session. The plan agent does NOT pre-verify candidate proof bodies via `lean_run_code` / `lean_multi_attempt`. Transient sorries inside the prover-built substep helpers remain acceptable.",
  "mode": "parallel",
  "startedAt": "2026-05-11T06:32:15Z",
  "plan": {
    "status": "done",
    "durationSecs": 416
  },
  "prover": {
    "status": "done",
    "durationSecs": 884
  },
  "provers": {
    "AlgebraicJacobian_Cohomology_MayerVietoris": {
      "file": "AlgebraicJacobian/Cohomology/MayerVietoris.lean",
      "status": "done"
    }
  },
  "review": {
    "status": "done",
    "durationSecs": 330
  },
  "sorry_count": 319,
  "finalize": {
    "innerGit": {
      "sha": "f31f5e3"
    },
    "lake": {
      "ok": true,
      "durationSecs": 29
    },
    "blueprint": {
      "ok": true,
      "durationSecs": 6
    }
  },
  "completedAt": "2026-05-11T07:21:09Z",
  "wallTimeSecs": 2934
}