{
  "iteration": 19,
  "stage": "prover  (iteration 018 \u2014 Path-2 Mayer-Vietoris LES composition-is-zero lemma `HModule'_toBiprod_fromBiprod`, refactor-then-prover phase. The iter-017 prover round closed `AlgebraicGeometry.Scheme.HModule'_toBiprod` and `AlgebraicGeometry.Scheme.HModule'_fromBiprod` cleanly: sorry count `9 \u2192 9` (the prover collapsed the refactor + prover sub-phases into a single Edit; the transient `9 \u2192 11 \u2192 9` trajectory was condensed), kernel-only axioms on both, the per-fiber `rfl` compatibility `((HModule'_cohomologyPresheaf k F n).obj (op X) : Type u) = HModule' k F n X` continues to hold, bodies adopted as the probe-confirmed term-mode one-liners with the in-namespace short name `HModule'_cohomologyPresheaf` and the standard `MayerVietorisSquare` accessors. Iter-018 plan-agent has scoped + probe-confirmed the next single-declaration sub-step: the **third Mayer-Vietoris LES building block** `Scheme.HModule'_toBiprod_fromBiprod` \u2014 a `@[reassoc (attr := simp)]`-attributed lemma asserting `HModule'_toBiprod k S F n \u226b HModule'_fromBiprod k S F n = 0`, mirror of Mathlib's `MayerVietorisSquare.toBiprod_fromBiprod` (file `Mathlib/CategoryTheory/Sites/SheafCohomology/MayerVietoris.lean`, L72\u201375). Body the verbatim Mathlib `simp only` proof (every rewrite component is value-category-agnostic and transfers cleanly). Connecting hom `\u03b4` deferred to iter-019+ because it requires a `Sheaf J (ModuleCat k)`-flavored `MayerVietorisSquare.shortComplex_shortExact` analog (Mathlib's is built from `AddCommGrpCat.free`-yoneda; the `ModuleCat k` flavour requires a parallel construction with `ModuleCat.free k`-yoneda + `isPushoutAddCommGrpFreeSheaf`-analog, multi-iteration substantive work). Iter-018 sorry count `9 \u2192 10 \u2192 9` over the iteration. Refactor agent runs first to scaffold; prover agent then closes.)",
  "mode": "parallel",
  "startedAt": "2026-05-08T05:07:17Z",
  "plan": {
    "status": "done",
    "durationSecs": 1190
  },
  "prover": {
    "status": "done",
    "durationSecs": 246
  },
  "provers": {
    "AlgebraicJacobian_Cohomology_StructureSheafModuleK": {
      "file": "AlgebraicJacobian/Cohomology/StructureSheafModuleK.lean",
      "status": "done"
    }
  },
  "review": {
    "status": "done",
    "durationSecs": 743
  }
}